.gitignore
CHANGES.txt
MANIFEST.in
README.rst
setup.py
demo/Makefile
demo/make.bat
demo/source/code.txt
demo/source/conf.py
demo/source/conf.py.original
demo/source/glossary.txt
demo/source/index.txt
demo/source/miscmarkups.txt
demo/source/titles.txt
sphinx/__init__.py
sphinx.plonetheme.egg-info/PKG-INFO
sphinx.plonetheme.egg-info/SOURCES.txt
sphinx.plonetheme.egg-info/dependency_links.txt
sphinx.plonetheme.egg-info/entry_points.txt
sphinx.plonetheme.egg-info/namespace_packages.txt
sphinx.plonetheme.egg-info/not-zip-safe
sphinx.plonetheme.egg-info/requires.txt
sphinx.plonetheme.egg-info/top_level.txt
sphinx/plonetheme/__init__.py
sphinx/plonetheme/templates/plonetheme/layout.html
sphinx/plonetheme/templates/plonetheme/opensearch.xml
sphinx/plonetheme/templates/plonetheme/theme.conf
sphinx/plonetheme/templates/plonetheme/static/attention-icon.png
sphinx/plonetheme/templates/plonetheme/static/caution-icon.png
sphinx/plonetheme/templates/plonetheme/static/danger-icon.png
sphinx/plonetheme/templates/plonetheme/static/error-icon.png
sphinx/plonetheme/templates/plonetheme/static/external.png
sphinx/plonetheme/templates/plonetheme/static/favicon.ico
sphinx/plonetheme/templates/plonetheme/static/hint-icon.png
sphinx/plonetheme/templates/plonetheme/static/important-icon.png
sphinx/plonetheme/templates/plonetheme/static/news-icon.png
sphinx/plonetheme/templates/plonetheme/static/note-icon.png
sphinx/plonetheme/templates/plonetheme/static/plone-icon-64.png
sphinx/plonetheme/templates/plonetheme/static/plone.css
sphinx/plonetheme/templates/plonetheme/static/seealso-icon.png
sphinx/plonetheme/templates/plonetheme/static/tip-icon.png
sphinx/plonetheme/templates/plonetheme/static/warning-icon.png