Metadata-Version: 1.0
Name: sphinx.plonetheme
Version: 2.0
Summary: Addon for Plone
Home-page: https://github.com/collective/sphinx.plonetheme
Author: Gilles Lenfant
Author-email: gilles.lenfant@alterway.fr
License: GPL
Keywords: sphinx theme
Platform: UNKNOWN
Classifier: License :: OSI Approved :: GNU General Public License (GPL)
Classifier: Operating System :: OS Independent
Classifier: Programming Language :: Python
Classifier: Programming Language :: Python :: 2.6
Classifier: Programming Language :: Python :: 2.7
